README.rst
setup.py
cryptobalances/__init__.py
cryptobalances/checker.py
cryptobalances/config.py
cryptobalances/main.py
cryptobalances/validator.py
cryptobalances.egg-info/PKG-INFO
cryptobalances.egg-info/SOURCES.txt
cryptobalances.egg-info/dependency_links.txt
cryptobalances.egg-info/entry_points.txt
cryptobalances.egg-info/requires.txt
cryptobalances.egg-info/top_level.txt
cryptobalances/exchanges/__init__.py
cryptobalances/exchanges/changer.py
cryptobalances/exchanges/coinomat.py
cryptobalances/exchanges/poloniex.py
cryptobalances/exchanges/shapeshift.py
cryptobalances/services/__init__.py
cryptobalances/services/chain_cryptoid.py
cryptobalances/services/chain_so.py
cryptobalances/services/counterparty.py
cryptobalances/services/doge.py
cryptobalances/services/ethereum.py
cryptobalances/services/golos.py
cryptobalances/services/nem.py
cryptobalances/services/nxt.py
cryptobalances/services/omni.py
cryptobalances/services/openassets.py
cryptobalances/services/ripple.py
cryptobalances/services/steem.py
cryptobalances/services/zcash.py