Metadata-Version: 1.0
Name: cryptobalances
Version: 0.9.5
Summary: Python module for getting the balance of a various crypto currency
Home-page: https://github.com/AleksandrLeonov/Crypto-Balances
Author: Aliaksandr Leonau
Author-email: leonov.aleksandr.1987@gmail.com
License: UNKNOWN
Platform: Linux
